swinburne_smartrack/__init__.py
swinburne_smartrack/__main__.py
swinburne_smartrack/apps.py
swinburne_smartrack/ciscodevice.py
swinburne_smartrack/configuration.py
swinburne_smartrack/devicemanager.py
swinburne_smartrack/multidevicemanager.py
swinburne_smartrack/smartrack.py
swinburne_smartrack/smartracktui.py
swinburne_smartrack/skills_collect/__init__.py
swinburne_smartrack/skills_collect/skillscollect.py
swinburne_smartrack/skills_collect/skillssession.py
swinburne_smartrack/skills_collect/studentcollect.py
swinburne_smartrack/skills_collect/validateexamconfig.py
swinburne_smartrack-0.0.9.dist-info/licenses/LICENSE
swinburne_smartrack-0.0.9.dist-info/METADATA
swinburne_smartrack-0.0.9.dist-info/WHEEL
swinburne_smartrack-0.0.9.dist-info/entry_points.txt
swinburne_smartrack-0.0.9.dist-info/top_level.txt
swinburne_smartrack-0.0.9.dist-info/RECORD
