Metadata-Version: 2.4
Name: swinburne-smartrack
Version: 0.0.9
Summary: Tools to manage devices via Swinburne Cisco SmartRack
Author-email: Jason But <jbut@swin.edu.au>
License-Expression: MIT
Project-URL: Homepage, https://github.com/jason-but/swinburne-smartrack
Project-URL: Issues, https://github.com/jason-but/swinburne-smartrack/issues
Classifier: Programming Language :: Python :: 3
Classifier: Operating System :: OS Independent
Requires-Python: >=3.11
License-File: LICENSE
Requires-Dist: logging
Requires-Dist: paramiko
Requires-Dist: pyparsing
Requires-Dist: pythondialog
Requires-Dist: requests
Requires-Dist: rich
Requires-Dist: tomli_w
Requires-Dist: tomlkit
Dynamic: license-file
